more_dfply/__init__.py
more_dfply/facets.py
more_dfply/more_dfply.py
more_dfply/symbolic.py
more_dfply-0.2.11.dist-info/WHEEL
more_dfply-0.2.11.dist-info/METADATA
more_dfply-0.2.11.dist-info/RECORD
