Metadata-Version: 2.1
Name: more-dfply
Version: 0.2.11
Summary: Helper functions for the dfply package
Author: Todd Iverson
Author-email: tiverson@winona.edu
Requires-Python: >=3.7,<4.0
Classifier: Programming Language :: Python :: 3
Classifier: Programming Language :: Python :: 3.7
Classifier: Programming Language :: Python :: 3.8
Classifier: Programming Language :: Python :: 3.9
Classifier: Programming Language :: Python :: 3.10
Classifier: Programming Language :: Python :: 3.11
Requires-Dist: composable (>=0.2.5,<0.3.0)
Requires-Dist: dfply (>=0.3.3,<0.4.0)
